package com.viber.voip.messages.ui;

class ap
  implements Runnable
{
  ap(ao paramao, int paramInt) {}
  
  /* Error */
  public void run()
  {
    // Byte code:
    //   0: aload_0
    //   1: getfield 14	com/viber/voip/messages/ui/ap:b	Lcom/viber/voip/messages/ui/ao;
    //   4: getfield 28	com/viber/voip/messages/ui/ao:c	Lcom/viber/voip/messages/ui/aj;
    //   7: iconst_1
    //   8: invokestatic 33	com/viber/voip/messages/ui/aj:a	(Lcom/viber/voip/messages/ui/aj;Z)V
    //   11: aload_0
    //   12: getfield 16	com/viber/voip/messages/ui/ap:a	I
    //   15: ldc 35
    //   17: invokestatic 41	com/viber/voip/stickers/b/h:d	(ILjava/lang/String;)Z
    //   20: ifeq +46 -> 66
    //   23: ldc 35
    //   25: astore_3
    //   26: aload_0
    //   27: getfield 16	com/viber/voip/messages/ui/ap:a	I
    //   30: aload_3
    //   31: invokestatic 41	com/viber/voip/stickers/b/h:d	(ILjava/lang/String;)Z
    //   34: ifeq +42 -> 76
    //   37: aload_0
    //   38: getfield 14	com/viber/voip/messages/ui/ap:b	Lcom/viber/voip/messages/ui/ao;
    //   41: getfield 28	com/viber/voip/messages/ui/ao:c	Lcom/viber/voip/messages/ui/aj;
    //   44: invokestatic 44	com/viber/voip/messages/ui/aj:b	(Lcom/viber/voip/messages/ui/aj;)Lcom/viber/voip/stickers/r;
    //   47: aload_0
    //   48: getfield 16	com/viber/voip/messages/ui/ap:a	I
    //   51: invokevirtual 50	com/viber/voip/stickers/r:i	(I)V
    //   54: aload_0
    //   55: getfield 14	com/viber/voip/messages/ui/ap:b	Lcom/viber/voip/messages/ui/ao;
    //   58: getfield 28	com/viber/voip/messages/ui/ao:c	Lcom/viber/voip/messages/ui/aj;
    //   61: iconst_0
    //   62: invokestatic 33	com/viber/voip/messages/ui/aj:a	(Lcom/viber/voip/messages/ui/aj;Z)V
    //   65: return
    //   66: getstatic 55	com/viber/voip/stickers/an:j	I
    //   69: invokestatic 61	java/lang/String:valueOf	(I)Ljava/lang/String;
    //   72: astore_3
    //   73: goto -47 -> 26
    //   76: getstatic 66	com/viber/voip/dk:a	Lcom/viber/voip/dk;
    //   79: invokestatic 71	com/viber/voip/dc:a	(Lcom/viber/voip/dk;)Landroid/os/Handler;
    //   82: new 73	com/viber/voip/messages/ui/aq
    //   85: dup
    //   86: aload_0
    //   87: invokespecial 76	com/viber/voip/messages/ui/aq:<init>	(Lcom/viber/voip/messages/ui/ap;)V
    //   90: invokevirtual 82	android/os/Handler:post	(Ljava/lang/Runnable;)Z
    //   93: pop
    //   94: goto -40 -> 54
    //   97: astore_2
    //   98: aload_2
    //   99: invokevirtual 85	java/lang/Exception:printStackTrace	()V
    //   102: aload_0
    //   103: getfield 14	com/viber/voip/messages/ui/ap:b	Lcom/viber/voip/messages/ui/ao;
    //   106: getfield 28	com/viber/voip/messages/ui/ao:c	Lcom/viber/voip/messages/ui/aj;
    //   109: iconst_0
    //   110: invokestatic 33	com/viber/voip/messages/ui/aj:a	(Lcom/viber/voip/messages/ui/aj;Z)V
    //   113: return
    //   114: astore_1
    //   115: aload_0
    //   116: getfield 14	com/viber/voip/messages/ui/ap:b	Lcom/viber/voip/messages/ui/ao;
    //   119: getfield 28	com/viber/voip/messages/ui/ao:c	Lcom/viber/voip/messages/ui/aj;
    //   122: iconst_0
    //   123: invokestatic 33	com/viber/voip/messages/ui/aj:a	(Lcom/viber/voip/messages/ui/aj;Z)V
    //   126: aload_1
    //   127: athrow
    // Local variable table:
    //   start	length	slot	name	signature
    //   0	128	0	this	ap
    //   114	13	1	localObject	Object
    //   97	2	2	localException	java.lang.Exception
    //   25	48	3	str	java.lang.String
    // Exception table:
    //   from	to	target	type
    //   11	23	97	java/lang/Exception
    //   26	54	97	java/lang/Exception
    //   66	73	97	java/lang/Exception
    //   76	94	97	java/lang/Exception
    //   11	23	114	finally
    //   26	54	114	finally
    //   66	73	114	finally
    //   76	94	114	finally
    //   98	102	114	finally
  }
}


/* Location:           C:\Users\pooya\Desktop\ac.jar
 * Qualified Name:     com.viber.voip.messages.ui.ap
 * JD-Core Version:    0.7.0.1
 */