package com.android.music.player.a;

import android.os.IBinder;
import android.os.Parcel;

class c
  implements a
{
  private IBinder a;
  
  c(IBinder paramIBinder)
  {
    this.a = paramIBinder;
  }
  
  public boolean A()
  {
    Parcel localParcel1 = Parcel.obtain();
    Parcel localParcel2 = Parcel.obtain();
    try
    {
      localParcel1.writeInterfaceToken("com.android.music.player.service.ICorePlayerService");
      this.a.transact(31, localParcel1, localParcel2, 0);
      localParcel2.readException();
      int i = localParcel2.readInt();
      boolean bool = false;
      if (i != 0) {
        bool = true;
      }
      return bool;
    }
    finally
    {
      localParcel2.recycle();
      localParcel1.recycle();
    }
  }
  
  public boolean B()
  {
    Parcel localParcel1 = Parcel.obtain();
    Parcel localParcel2 = Parcel.obtain();
    try
    {
      localParcel1.writeInterfaceToken("com.android.music.player.service.ICorePlayerService");
      this.a.transact(32, localParcel1, localParcel2, 0);
      localParcel2.readException();
      int i = localParcel2.readInt();
      boolean bool = false;
      if (i != 0) {
        bool = true;
      }
      return bool;
    }
    finally
    {
      localParcel2.recycle();
      localParcel1.recycle();
    }
  }
  
  public void C()
  {
    Parcel localParcel1 = Parcel.obtain();
    Parcel localParcel2 = Parcel.obtain();
    try
    {
      localParcel1.writeInterfaceToken("com.android.music.player.service.ICorePlayerService");
      this.a.transact(33, localParcel1, localParcel2, 0);
      localParcel2.readException();
      return;
    }
    finally
    {
      localParcel2.recycle();
      localParcel1.recycle();
    }
  }
  
  public void D()
  {
    Parcel localParcel1 = Parcel.obtain();
    Parcel localParcel2 = Parcel.obtain();
    try
    {
      localParcel1.writeInterfaceToken("com.android.music.player.service.ICorePlayerService");
      this.a.transact(34, localParcel1, localParcel2, 0);
      localParcel2.readException();
      return;
    }
    finally
    {
      localParcel2.recycle();
      localParcel1.recycle();
    }
  }
  
  public void E()
  {
    Parcel localParcel1 = Parcel.obtain();
    Parcel localParcel2 = Parcel.obtain();
    try
    {
      localParcel1.writeInterfaceToken("com.android.music.player.service.ICorePlayerService");
      this.a.transact(35, localParcel1, localParcel2, 0);
      localParcel2.readException();
      return;
    }
    finally
    {
      localParcel2.recycle();
      localParcel1.recycle();
    }
  }
  
  public void F()
  {
    Parcel localParcel1 = Parcel.obtain();
    Parcel localParcel2 = Parcel.obtain();
    try
    {
      localParcel1.writeInterfaceToken("com.android.music.player.service.ICorePlayerService");
      this.a.transact(36, localParcel1, localParcel2, 0);
      localParcel2.readException();
      return;
    }
    finally
    {
      localParcel2.recycle();
      localParcel1.recycle();
    }
  }
  
  public void G()
  {
    Parcel localParcel1 = Parcel.obtain();
    Parcel localParcel2 = Parcel.obtain();
    try
    {
      localParcel1.writeInterfaceToken("com.android.music.player.service.ICorePlayerService");
      this.a.transact(37, localParcel1, localParcel2, 0);
      localParcel2.readException();
      return;
    }
    finally
    {
      localParcel2.recycle();
      localParcel1.recycle();
    }
  }
  
  public void H()
  {
    Parcel localParcel1 = Parcel.obtain();
    Parcel localParcel2 = Parcel.obtain();
    try
    {
      localParcel1.writeInterfaceToken("com.android.music.player.service.ICorePlayerService");
      this.a.transact(38, localParcel1, localParcel2, 0);
      localParcel2.readException();
      return;
    }
    finally
    {
      localParcel2.recycle();
      localParcel1.recycle();
    }
  }
  
  public void I()
  {
    Parcel localParcel1 = Parcel.obtain();
    Parcel localParcel2 = Parcel.obtain();
    try
    {
      localParcel1.writeInterfaceToken("com.android.music.player.service.ICorePlayerService");
      this.a.transact(39, localParcel1, localParcel2, 0);
      localParcel2.readException();
      return;
    }
    finally
    {
      localParcel2.recycle();
      localParcel1.recycle();
    }
  }
  
  public void J()
  {
    Parcel localParcel1 = Parcel.obtain();
    Parcel localParcel2 = Parcel.obtain();
    try
    {
      localParcel1.writeInterfaceToken("com.android.music.player.service.ICorePlayerService");
      this.a.transact(40, localParcel1, localParcel2, 0);
      localParcel2.readException();
      return;
    }
    finally
    {
      localParcel2.recycle();
      localParcel1.recycle();
    }
  }
  
  public void K()
  {
    Parcel localParcel1 = Parcel.obtain();
    Parcel localParcel2 = Parcel.obtain();
    try
    {
      localParcel1.writeInterfaceToken("com.android.music.player.service.ICorePlayerService");
      this.a.transact(41, localParcel1, localParcel2, 0);
      localParcel2.readException();
      return;
    }
    finally
    {
      localParcel2.recycle();
      localParcel1.recycle();
    }
  }
  
  public void L()
  {
    Parcel localParcel1 = Parcel.obtain();
    Parcel localParcel2 = Parcel.obtain();
    try
    {
      localParcel1.writeInterfaceToken("com.android.music.player.service.ICorePlayerService");
      this.a.transact(42, localParcel1, localParcel2, 0);
      localParcel2.readException();
      return;
    }
    finally
    {
      localParcel2.recycle();
      localParcel1.recycle();
    }
  }
  
  public void M()
  {
    Parcel localParcel1 = Parcel.obtain();
    Parcel localParcel2 = Parcel.obtain();
    try
    {
      localParcel1.writeInterfaceToken("com.android.music.player.service.ICorePlayerService");
      this.a.transact(43, localParcel1, localParcel2, 0);
      localParcel2.readException();
      return;
    }
    finally
    {
      localParcel2.recycle();
      localParcel1.recycle();
    }
  }
  
  public void N()
  {
    Parcel localParcel1 = Parcel.obtain();
    Parcel localParcel2 = Parcel.obtain();
    try
    {
      localParcel1.writeInterfaceToken("com.android.music.player.service.ICorePlayerService");
      this.a.transact(44, localParcel1, localParcel2, 0);
      localParcel2.readException();
      return;
    }
    finally
    {
      localParcel2.recycle();
      localParcel1.recycle();
    }
  }
  
  public void O()
  {
    Parcel localParcel1 = Parcel.obtain();
    Parcel localParcel2 = Parcel.obtain();
    try
    {
      localParcel1.writeInterfaceToken("com.android.music.player.service.ICorePlayerService");
      this.a.transact(45, localParcel1, localParcel2, 0);
      localParcel2.readException();
      return;
    }
    finally
    {
      localParcel2.recycle();
      localParcel1.recycle();
    }
  }
  
  public void P()
  {
    Parcel localParcel1 = Parcel.obtain();
    Parcel localParcel2 = Parcel.obtain();
    try
    {
      localParcel1.writeInterfaceToken("com.android.music.player.service.ICorePlayerService");
      this.a.transact(46, localParcel1, localParcel2, 0);
      localParcel2.readException();
      return;
    }
    finally
    {
      localParcel2.recycle();
      localParcel1.recycle();
    }
  }
  
  public void Q()
  {
    Parcel localParcel1 = Parcel.obtain();
    Parcel localParcel2 = Parcel.obtain();
    try
    {
      localParcel1.writeInterfaceToken("com.android.music.player.service.ICorePlayerService");
      this.a.transact(47, localParcel1, localParcel2, 0);
      localParcel2.readException();
      return;
    }
    finally
    {
      localParcel2.recycle();
      localParcel1.recycle();
    }
  }
  
  public boolean R()
  {
    Parcel localParcel1 = Parcel.obtain();
    Parcel localParcel2 = Parcel.obtain();
    try
    {
      localParcel1.writeInterfaceToken("com.android.music.player.service.ICorePlayerService");
      this.a.transact(48, localParcel1, localParcel2, 0);
      localParcel2.readException();
      int i = localParcel2.readInt();
      boolean bool = false;
      if (i != 0) {
        bool = true;
      }
      return bool;
    }
    finally
    {
      localParcel2.recycle();
      localParcel1.recycle();
    }
  }
  
  public void S()
  {
    Parcel localParcel1 = Parcel.obtain();
    Parcel localParcel2 = Parcel.obtain();
    try
    {
      localParcel1.writeInterfaceToken("com.android.music.player.service.ICorePlayerService");
      this.a.transact(49, localParcel1, localParcel2, 0);
      localParcel2.readException();
      return;
    }
    finally
    {
      localParcel2.recycle();
      localParcel1.recycle();
    }
  }
  
  public void a()
  {
    Parcel localParcel1 = Parcel.obtain();
    Parcel localParcel2 = Parcel.obtain();
    try
    {
      localParcel1.writeInterfaceToken("com.android.music.player.service.ICorePlayerService");
      this.a.transact(1, localParcel1, localParcel2, 0);
      localParcel2.readException();
      return;
    }
    finally
    {
      localParcel2.recycle();
      localParcel1.recycle();
    }
  }
  
  public void a(boolean paramBoolean)
  {
    Parcel localParcel1 = Parcel.obtain();
    Parcel localParcel2 = Parcel.obtain();
    try
    {
      localParcel1.writeInterfaceToken("com.android.music.player.service.ICorePlayerService");
      int i = 0;
      if (paramBoolean) {
        i = 1;
      }
      localParcel1.writeInt(i);
      this.a.transact(7, localParcel1, localParcel2, 0);
      localParcel2.readException();
      return;
    }
    finally
    {
      localParcel2.recycle();
      localParcel1.recycle();
    }
  }
  
  /* Error */
  public void a(int[] paramArrayOfInt)
  {
    // Byte code:
    //   0: invokestatic 23	android/os/Parcel:obtain	()Landroid/os/Parcel;
    //   3: astore_2
    //   4: invokestatic 23	android/os/Parcel:obtain	()Landroid/os/Parcel;
    //   7: astore_3
    //   8: aload_2
    //   9: ldc 25
    //   11: invokevirtual 29	android/os/Parcel:writeInterfaceToken	(Ljava/lang/String;)V
    //   14: aload_1
    //   15: ifnonnull +41 -> 56
    //   18: aload_2
    //   19: iconst_m1
    //   20: invokevirtual 68	android/os/Parcel:writeInt	(I)V
    //   23: aload_0
    //   24: getfield 15	com/android/music/player/a/c:a	Landroid/os/IBinder;
    //   27: bipush 25
    //   29: aload_2
    //   30: aload_3
    //   31: iconst_0
    //   32: invokeinterface 35 5 0
    //   37: pop
    //   38: aload_3
    //   39: invokevirtual 38	android/os/Parcel:readException	()V
    //   42: aload_3
    //   43: aload_1
    //   44: invokevirtual 72	android/os/Parcel:readIntArray	([I)V
    //   47: aload_3
    //   48: invokevirtual 45	android/os/Parcel:recycle	()V
    //   51: aload_2
    //   52: invokevirtual 45	android/os/Parcel:recycle	()V
    //   55: return
    //   56: aload_2
    //   57: aload_1
    //   58: arraylength
    //   59: invokevirtual 68	android/os/Parcel:writeInt	(I)V
    //   62: goto -39 -> 23
    //   65: astore 4
    //   67: aload_3
    //   68: invokevirtual 45	android/os/Parcel:recycle	()V
    //   71: aload_2
    //   72: invokevirtual 45	android/os/Parcel:recycle	()V
    //   75: aload 4
    //   77: athrow
    // Local variable table:
    //   start	length	slot	name	signature
    //   0	78	0	this	c
    //   0	78	1	paramArrayOfInt	int[]
    //   3	69	2	localParcel1	Parcel
    //   7	61	3	localParcel2	Parcel
    //   65	11	4	localObject	Object
    // Exception table:
    //   from	to	target	type
    //   8	14	65	finally
    //   18	23	65	finally
    //   23	47	65	finally
    //   56	62	65	finally
  }
  
  public IBinder asBinder()
  {
    return this.a;
  }
  
  public int b()
  {
    Parcel localParcel1 = Parcel.obtain();
    Parcel localParcel2 = Parcel.obtain();
    try
    {
      localParcel1.writeInterfaceToken("com.android.music.player.service.ICorePlayerService");
      this.a.transact(2, localParcel1, localParcel2, 0);
      localParcel2.readException();
      int i = localParcel2.readInt();
      return i;
    }
    finally
    {
      localParcel2.recycle();
      localParcel1.recycle();
    }
  }
  
  public void b(boolean paramBoolean)
  {
    Parcel localParcel1 = Parcel.obtain();
    Parcel localParcel2 = Parcel.obtain();
    try
    {
      localParcel1.writeInterfaceToken("com.android.music.player.service.ICorePlayerService");
      int i = 0;
      if (paramBoolean) {
        i = 1;
      }
      localParcel1.writeInt(i);
      this.a.transact(8, localParcel1, localParcel2, 0);
      localParcel2.readException();
      return;
    }
    finally
    {
      localParcel2.recycle();
      localParcel1.recycle();
    }
  }
  
  public int c()
  {
    Parcel localParcel1 = Parcel.obtain();
    Parcel localParcel2 = Parcel.obtain();
    try
    {
      localParcel1.writeInterfaceToken("com.android.music.player.service.ICorePlayerService");
      this.a.transact(3, localParcel1, localParcel2, 0);
      localParcel2.readException();
      int i = localParcel2.readInt();
      return i;
    }
    finally
    {
      localParcel2.recycle();
      localParcel1.recycle();
    }
  }
  
  public void c(boolean paramBoolean)
  {
    Parcel localParcel1 = Parcel.obtain();
    Parcel localParcel2 = Parcel.obtain();
    try
    {
      localParcel1.writeInterfaceToken("com.android.music.player.service.ICorePlayerService");
      int i = 0;
      if (paramBoolean) {
        i = 1;
      }
      localParcel1.writeInt(i);
      this.a.transact(19, localParcel1, localParcel2, 0);
      localParcel2.readException();
      return;
    }
    finally
    {
      localParcel2.recycle();
      localParcel1.recycle();
    }
  }
  
  public String d()
  {
    Parcel localParcel1 = Parcel.obtain();
    Parcel localParcel2 = Parcel.obtain();
    try
    {
      localParcel1.writeInterfaceToken("com.android.music.player.service.ICorePlayerService");
      this.a.transact(4, localParcel1, localParcel2, 0);
      localParcel2.readException();
      String str = localParcel2.readString();
      return str;
    }
    finally
    {
      localParcel2.recycle();
      localParcel1.recycle();
    }
  }
  
  public void e()
  {
    Parcel localParcel1 = Parcel.obtain();
    Parcel localParcel2 = Parcel.obtain();
    try
    {
      localParcel1.writeInterfaceToken("com.android.music.player.service.ICorePlayerService");
      this.a.transact(5, localParcel1, localParcel2, 0);
      localParcel2.readException();
      return;
    }
    finally
    {
      localParcel2.recycle();
      localParcel1.recycle();
    }
  }
  
  public int f()
  {
    Parcel localParcel1 = Parcel.obtain();
    Parcel localParcel2 = Parcel.obtain();
    try
    {
      localParcel1.writeInterfaceToken("com.android.music.player.service.ICorePlayerService");
      this.a.transact(6, localParcel1, localParcel2, 0);
      localParcel2.readException();
      int i = localParcel2.readInt();
      return i;
    }
    finally
    {
      localParcel2.recycle();
      localParcel1.recycle();
    }
  }
  
  /* Error */
  public com.android.music.player.data.MusicAlbumInfo g()
  {
    // Byte code:
    //   0: invokestatic 23	android/os/Parcel:obtain	()Landroid/os/Parcel;
    //   3: astore_1
    //   4: invokestatic 23	android/os/Parcel:obtain	()Landroid/os/Parcel;
    //   7: astore_2
    //   8: aload_1
    //   9: ldc 25
    //   11: invokevirtual 29	android/os/Parcel:writeInterfaceToken	(Ljava/lang/String;)V
    //   14: aload_0
    //   15: getfield 15	com/android/music/player/a/c:a	Landroid/os/IBinder;
    //   18: bipush 9
    //   20: aload_1
    //   21: aload_2
    //   22: iconst_0
    //   23: invokeinterface 35 5 0
    //   28: pop
    //   29: aload_2
    //   30: invokevirtual 38	android/os/Parcel:readException	()V
    //   33: aload_2
    //   34: invokevirtual 42	android/os/Parcel:readInt	()I
    //   37: ifeq +28 -> 65
    //   40: getstatic 91	com/android/music/player/data/MusicAlbumInfo:CREATOR	Landroid/os/Parcelable$Creator;
    //   43: aload_2
    //   44: invokeinterface 97 2 0
    //   49: checkcast 87	com/android/music/player/data/MusicAlbumInfo
    //   52: astore 5
    //   54: aload_2
    //   55: invokevirtual 45	android/os/Parcel:recycle	()V
    //   58: aload_1
    //   59: invokevirtual 45	android/os/Parcel:recycle	()V
    //   62: aload 5
    //   64: areturn
    //   65: aconst_null
    //   66: astore 5
    //   68: goto -14 -> 54
    //   71: astore_3
    //   72: aload_2
    //   73: invokevirtual 45	android/os/Parcel:recycle	()V
    //   76: aload_1
    //   77: invokevirtual 45	android/os/Parcel:recycle	()V
    //   80: aload_3
    //   81: athrow
    // Local variable table:
    //   start	length	slot	name	signature
    //   0	82	0	this	c
    //   3	74	1	localParcel1	Parcel
    //   7	66	2	localParcel2	Parcel
    //   71	10	3	localObject	Object
    //   52	15	5	localMusicAlbumInfo	com.android.music.player.data.MusicAlbumInfo
    // Exception table:
    //   from	to	target	type
    //   8	54	71	finally
  }
  
  public int h()
  {
    Parcel localParcel1 = Parcel.obtain();
    Parcel localParcel2 = Parcel.obtain();
    try
    {
      localParcel1.writeInterfaceToken("com.android.music.player.service.ICorePlayerService");
      this.a.transact(10, localParcel1, localParcel2, 0);
      localParcel2.readException();
      int i = localParcel2.readInt();
      return i;
    }
    finally
    {
      localParcel2.recycle();
      localParcel1.recycle();
    }
  }
  
  public int i()
  {
    Parcel localParcel1 = Parcel.obtain();
    Parcel localParcel2 = Parcel.obtain();
    try
    {
      localParcel1.writeInterfaceToken("com.android.music.player.service.ICorePlayerService");
      this.a.transact(11, localParcel1, localParcel2, 0);
      localParcel2.readException();
      int i = localParcel2.readInt();
      return i;
    }
    finally
    {
      localParcel2.recycle();
      localParcel1.recycle();
    }
  }
  
  public int j()
  {
    Parcel localParcel1 = Parcel.obtain();
    Parcel localParcel2 = Parcel.obtain();
    try
    {
      localParcel1.writeInterfaceToken("com.android.music.player.service.ICorePlayerService");
      this.a.transact(12, localParcel1, localParcel2, 0);
      localParcel2.readException();
      int i = localParcel2.readInt();
      return i;
    }
    finally
    {
      localParcel2.recycle();
      localParcel1.recycle();
    }
  }
  
  public boolean k()
  {
    Parcel localParcel1 = Parcel.obtain();
    Parcel localParcel2 = Parcel.obtain();
    try
    {
      localParcel1.writeInterfaceToken("com.android.music.player.service.ICorePlayerService");
      this.a.transact(13, localParcel1, localParcel2, 0);
      localParcel2.readException();
      int i = localParcel2.readInt();
      boolean bool = false;
      if (i != 0) {
        bool = true;
      }
      return bool;
    }
    finally
    {
      localParcel2.recycle();
      localParcel1.recycle();
    }
  }
  
  public int l()
  {
    Parcel localParcel1 = Parcel.obtain();
    Parcel localParcel2 = Parcel.obtain();
    try
    {
      localParcel1.writeInterfaceToken("com.android.music.player.service.ICorePlayerService");
      this.a.transact(14, localParcel1, localParcel2, 0);
      localParcel2.readException();
      int i = localParcel2.readInt();
      return i;
    }
    finally
    {
      localParcel2.recycle();
      localParcel1.recycle();
    }
  }
  
  public String m()
  {
    Parcel localParcel1 = Parcel.obtain();
    Parcel localParcel2 = Parcel.obtain();
    try
    {
      localParcel1.writeInterfaceToken("com.android.music.player.service.ICorePlayerService");
      this.a.transact(15, localParcel1, localParcel2, 0);
      localParcel2.readException();
      String str = localParcel2.readString();
      return str;
    }
    finally
    {
      localParcel2.recycle();
      localParcel1.recycle();
    }
  }
  
  public String n()
  {
    Parcel localParcel1 = Parcel.obtain();
    Parcel localParcel2 = Parcel.obtain();
    try
    {
      localParcel1.writeInterfaceToken("com.android.music.player.service.ICorePlayerService");
      this.a.transact(16, localParcel1, localParcel2, 0);
      localParcel2.readException();
      String str = localParcel2.readString();
      return str;
    }
    finally
    {
      localParcel2.recycle();
      localParcel1.recycle();
    }
  }
  
  public int o()
  {
    Parcel localParcel1 = Parcel.obtain();
    Parcel localParcel2 = Parcel.obtain();
    try
    {
      localParcel1.writeInterfaceToken("com.android.music.player.service.ICorePlayerService");
      this.a.transact(17, localParcel1, localParcel2, 0);
      localParcel2.readException();
      int i = localParcel2.readInt();
      return i;
    }
    finally
    {
      localParcel2.recycle();
      localParcel1.recycle();
    }
  }
  
  public String p()
  {
    Parcel localParcel1 = Parcel.obtain();
    Parcel localParcel2 = Parcel.obtain();
    try
    {
      localParcel1.writeInterfaceToken("com.android.music.player.service.ICorePlayerService");
      this.a.transact(18, localParcel1, localParcel2, 0);
      localParcel2.readException();
      String str = localParcel2.readString();
      return str;
    }
    finally
    {
      localParcel2.recycle();
      localParcel1.recycle();
    }
  }
  
  public void q()
  {
    Parcel localParcel1 = Parcel.obtain();
    Parcel localParcel2 = Parcel.obtain();
    try
    {
      localParcel1.writeInterfaceToken("com.android.music.player.service.ICorePlayerService");
      this.a.transact(20, localParcel1, localParcel2, 0);
      localParcel2.readException();
      return;
    }
    finally
    {
      localParcel2.recycle();
      localParcel1.recycle();
    }
  }
  
  public int r()
  {
    Parcel localParcel1 = Parcel.obtain();
    Parcel localParcel2 = Parcel.obtain();
    try
    {
      localParcel1.writeInterfaceToken("com.android.music.player.service.ICorePlayerService");
      this.a.transact(21, localParcel1, localParcel2, 0);
      localParcel2.readException();
      int i = localParcel2.readInt();
      return i;
    }
    finally
    {
      localParcel2.recycle();
      localParcel1.recycle();
    }
  }
  
  public int s()
  {
    Parcel localParcel1 = Parcel.obtain();
    Parcel localParcel2 = Parcel.obtain();
    try
    {
      localParcel1.writeInterfaceToken("com.android.music.player.service.ICorePlayerService");
      this.a.transact(22, localParcel1, localParcel2, 0);
      localParcel2.readException();
      int i = localParcel2.readInt();
      return i;
    }
    finally
    {
      localParcel2.recycle();
      localParcel1.recycle();
    }
  }
  
  public void t()
  {
    Parcel localParcel1 = Parcel.obtain();
    Parcel localParcel2 = Parcel.obtain();
    try
    {
      localParcel1.writeInterfaceToken("com.android.music.player.service.ICorePlayerService");
      this.a.transact(23, localParcel1, localParcel2, 0);
      localParcel2.readException();
      return;
    }
    finally
    {
      localParcel2.recycle();
      localParcel1.recycle();
    }
  }
  
  public void u()
  {
    Parcel localParcel1 = Parcel.obtain();
    Parcel localParcel2 = Parcel.obtain();
    try
    {
      localParcel1.writeInterfaceToken("com.android.music.player.service.ICorePlayerService");
      this.a.transact(24, localParcel1, localParcel2, 0);
      localParcel2.readException();
      return;
    }
    finally
    {
      localParcel2.recycle();
      localParcel1.recycle();
    }
  }
  
  public int v()
  {
    Parcel localParcel1 = Parcel.obtain();
    Parcel localParcel2 = Parcel.obtain();
    try
    {
      localParcel1.writeInterfaceToken("com.android.music.player.service.ICorePlayerService");
      this.a.transact(26, localParcel1, localParcel2, 0);
      localParcel2.readException();
      int i = localParcel2.readInt();
      return i;
    }
    finally
    {
      localParcel2.recycle();
      localParcel1.recycle();
    }
  }
  
  public int w()
  {
    Parcel localParcel1 = Parcel.obtain();
    Parcel localParcel2 = Parcel.obtain();
    try
    {
      localParcel1.writeInterfaceToken("com.android.music.player.service.ICorePlayerService");
      this.a.transact(27, localParcel1, localParcel2, 0);
      localParcel2.readException();
      int i = localParcel2.readInt();
      return i;
    }
    finally
    {
      localParcel2.recycle();
      localParcel1.recycle();
    }
  }
  
  public boolean x()
  {
    Parcel localParcel1 = Parcel.obtain();
    Parcel localParcel2 = Parcel.obtain();
    try
    {
      localParcel1.writeInterfaceToken("com.android.music.player.service.ICorePlayerService");
      this.a.transact(28, localParcel1, localParcel2, 0);
      localParcel2.readException();
      int i = localParcel2.readInt();
      boolean bool = false;
      if (i != 0) {
        bool = true;
      }
      return bool;
    }
    finally
    {
      localParcel2.recycle();
      localParcel1.recycle();
    }
  }
  
  public int y()
  {
    Parcel localParcel1 = Parcel.obtain();
    Parcel localParcel2 = Parcel.obtain();
    try
    {
      localParcel1.writeInterfaceToken("com.android.music.player.service.ICorePlayerService");
      this.a.transact(29, localParcel1, localParcel2, 0);
      localParcel2.readException();
      int i = localParcel2.readInt();
      return i;
    }
    finally
    {
      localParcel2.recycle();
      localParcel1.recycle();
    }
  }
  
  public void z()
  {
    Parcel localParcel1 = Parcel.obtain();
    Parcel localParcel2 = Parcel.obtain();
    try
    {
      localParcel1.writeInterfaceToken("com.android.music.player.service.ICorePlayerService");
      this.a.transact(30, localParcel1, localParcel2, 0);
      localParcel2.readException();
      return;
    }
    finally
    {
      localParcel2.recycle();
      localParcel1.recycle();
    }
  }
}


/* Location:           C:\Users\pooya\Desktop\bc.jar
 * Qualified Name:     com.android.music.player.a.c
 * JD-Core Version:    0.7.0.1
 */