package com.viber.voip.registration;

class de
{
  private final String a;
  private String b;
  
  public de(String paramString)
  {
    this(paramString, "1");
  }
  
  public de(String paramString1, String paramString2)
  {
    this.a = paramString1;
    this.b = paramString2;
  }
  
  /* Error */
  public df a(java.io.InputStream paramInputStream)
  {
    // Byte code:
    //   0: aconst_null
    //   1: astore_2
    //   2: aconst_null
    //   3: astore_3
    //   4: iconst_0
    //   5: istore 4
    //   7: aconst_null
    //   8: astore 5
    //   10: aconst_null
    //   11: astore 6
    //   13: aconst_null
    //   14: astore 7
    //   16: aload_1
    //   17: bipush 10
    //   19: ldc 27
    //   21: invokestatic 32	com/viber/voip/util/am:a	(Ljava/io/InputStream;II)[B
    //   24: astore 31
    //   26: aload 31
    //   28: astore 9
    //   30: new 34	java/io/ByteArrayInputStream
    //   33: dup
    //   34: aload 9
    //   36: invokespecial 37	java/io/ByteArrayInputStream:<init>	([B)V
    //   39: astore 10
    //   41: invokestatic 43	org/xmlpull/v1/XmlPullParserFactory:newInstance	()Lorg/xmlpull/v1/XmlPullParserFactory;
    //   44: invokevirtual 47	org/xmlpull/v1/XmlPullParserFactory:newPullParser	()Lorg/xmlpull/v1/XmlPullParser;
    //   47: astore 12
    //   49: aload 12
    //   51: aload 10
    //   53: ldc 49
    //   55: invokeinterface 55 3 0
    //   60: aload 12
    //   62: invokeinterface 59 1 0
    //   67: istore 15
    //   69: iconst_0
    //   70: istore 16
    //   72: aconst_null
    //   73: astore 17
    //   75: aconst_null
    //   76: astore 18
    //   78: aconst_null
    //   79: astore 19
    //   81: iload 15
    //   83: iconst_1
    //   84: if_icmpeq +308 -> 392
    //   87: iload 15
    //   89: iconst_2
    //   90: if_icmpne +106 -> 196
    //   93: aload 12
    //   95: invokeinterface 63 1 0
    //   100: astore 17
    //   102: aload_0
    //   103: getfield 19	com/viber/voip/registration/de:a	Ljava/lang/String;
    //   106: aload 17
    //   108: invokevirtual 69	java/lang/String:equalsIgnoreCase	(Ljava/lang/String;)Z
    //   111: ifeq +346 -> 457
    //   114: aload 18
    //   116: astore 20
    //   118: aload 17
    //   120: astore 21
    //   122: iload 16
    //   124: istore 22
    //   126: ldc 71
    //   128: astore 23
    //   130: aload 12
    //   132: invokeinterface 74 1 0
    //   137: istore 24
    //   139: iload 24
    //   141: istore 15
    //   143: aload 23
    //   145: astore 25
    //   147: iload 22
    //   149: istore 16
    //   151: aload 21
    //   153: astore 17
    //   155: aload 20
    //   157: astore 18
    //   159: aload 25
    //   161: astore 19
    //   163: goto -82 -> 81
    //   166: astore 8
    //   168: aload 8
    //   170: invokevirtual 77	java/io/IOException:printStackTrace	()V
    //   173: iconst_0
    //   174: newarray byte
    //   176: astore 9
    //   178: goto -148 -> 30
    //   181: astore 11
    //   183: new 24	java/io/IOException
    //   186: dup
    //   187: aload 11
    //   189: invokevirtual 80	org/xmlpull/v1/XmlPullParserException:getMessage	()Ljava/lang/String;
    //   192: invokespecial 82	java/io/IOException:<init>	(Ljava/lang/String;)V
    //   195: athrow
    //   196: iload 15
    //   198: iconst_4
    //   199: if_icmpne +304 -> 503
    //   202: aload 12
    //   204: invokeinterface 86 1 0
    //   209: istore 28
    //   211: aload 12
    //   213: invokeinterface 89 1 0
    //   218: astore 29
    //   220: ldc 71
    //   222: aload 17
    //   224: invokevirtual 69	java/lang/String:equalsIgnoreCase	(Ljava/lang/String;)Z
    //   227: ifeq +40 -> 267
    //   230: ldc 71
    //   232: aload 19
    //   234: invokevirtual 69	java/lang/String:equalsIgnoreCase	(Ljava/lang/String;)Z
    //   237: ifeq +30 -> 267
    //   240: iload 28
    //   242: ifne +25 -> 267
    //   245: aload 29
    //   247: invokevirtual 92	java/lang/String:trim	()Ljava/lang/String;
    //   250: astore 18
    //   252: aload 18
    //   254: aload_0
    //   255: getfield 21	com/viber/voip/registration/de:b	Ljava/lang/String;
    //   258: invokevirtual 69	java/lang/String:equalsIgnoreCase	(Ljava/lang/String;)Z
    //   261: ifeq +6 -> 267
    //   264: iconst_1
    //   265: istore 16
    //   267: ldc 94
    //   269: aload 17
    //   271: invokevirtual 69	java/lang/String:equalsIgnoreCase	(Ljava/lang/String;)Z
    //   274: ifeq +11 -> 285
    //   277: iload 28
    //   279: ifne +6 -> 285
    //   282: aload 29
    //   284: astore_2
    //   285: ldc 96
    //   287: aload 17
    //   289: invokevirtual 69	java/lang/String:equalsIgnoreCase	(Ljava/lang/String;)Z
    //   292: ifeq +11 -> 303
    //   295: iload 28
    //   297: ifne +6 -> 303
    //   300: aload 29
    //   302: astore_3
    //   303: ldc 98
    //   305: aload 17
    //   307: invokevirtual 69	java/lang/String:equalsIgnoreCase	(Ljava/lang/String;)Z
    //   310: ifeq +26 -> 336
    //   313: iload 28
    //   315: ifne +21 -> 336
    //   318: aload 29
    //   320: invokevirtual 92	java/lang/String:trim	()Ljava/lang/String;
    //   323: aload_0
    //   324: getfield 21	com/viber/voip/registration/de:b	Ljava/lang/String;
    //   327: invokevirtual 69	java/lang/String:equalsIgnoreCase	(Ljava/lang/String;)Z
    //   330: ifeq +6 -> 336
    //   333: iconst_1
    //   334: istore 4
    //   336: ldc 100
    //   338: aload 17
    //   340: invokevirtual 69	java/lang/String:equalsIgnoreCase	(Ljava/lang/String;)Z
    //   343: ifeq +12 -> 355
    //   346: iload 28
    //   348: ifne +7 -> 355
    //   351: aload 29
    //   353: astore 5
    //   355: ldc 102
    //   357: aload 17
    //   359: invokevirtual 69	java/lang/String:equalsIgnoreCase	(Ljava/lang/String;)Z
    //   362: ifeq +10 -> 372
    //   365: aload 29
    //   367: invokevirtual 92	java/lang/String:trim	()Ljava/lang/String;
    //   370: astore 6
    //   372: ldc 104
    //   374: aload 17
    //   376: invokevirtual 69	java/lang/String:equalsIgnoreCase	(Ljava/lang/String;)Z
    //   379: ifeq +101 -> 480
    //   382: aload 29
    //   384: invokevirtual 92	java/lang/String:trim	()Ljava/lang/String;
    //   387: astore 7
    //   389: goto +91 -> 480
    //   392: aload 19
    //   394: ifnonnull +37 -> 431
    //   397: new 24	java/io/IOException
    //   400: dup
    //   401: ldc 106
    //   403: invokespecial 82	java/io/IOException:<init>	(Ljava/lang/String;)V
    //   406: athrow
    //   407: astore 14
    //   409: new 24	java/io/IOException
    //   412: dup
    //   413: aload 14
    //   415: invokevirtual 80	org/xmlpull/v1/XmlPullParserException:getMessage	()Ljava/lang/String;
    //   418: invokespecial 82	java/io/IOException:<init>	(Ljava/lang/String;)V
    //   421: athrow
    //   422: astore 13
    //   424: aload_1
    //   425: invokevirtual 111	java/io/InputStream:close	()V
    //   428: aload 13
    //   430: athrow
    //   431: aload_1
    //   432: invokevirtual 111	java/io/InputStream:close	()V
    //   435: new 113	com/viber/voip/registration/df
    //   438: dup
    //   439: iload 16
    //   441: aload 18
    //   443: aload_2
    //   444: aload_3
    //   445: iload 4
    //   447: aload 5
    //   449: aload 6
    //   451: aload 7
    //   453: invokespecial 116	com/viber/voip/registration/df:<init>	(ZLjava/lang/String;Ljava/lang/String;Ljava/lang/String;ZLjava/lang/String;Ljava/lang/String;Ljava/lang/String;)V
    //   456: areturn
    //   457: aload 19
    //   459: astore 26
    //   461: aload 18
    //   463: astore 20
    //   465: aload 17
    //   467: astore 21
    //   469: iload 16
    //   471: istore 22
    //   473: aload 26
    //   475: astore 23
    //   477: goto -347 -> 130
    //   480: aload 19
    //   482: astore 30
    //   484: aload 18
    //   486: astore 20
    //   488: aload 17
    //   490: astore 21
    //   492: iload 16
    //   494: istore 22
    //   496: aload 30
    //   498: astore 23
    //   500: goto -370 -> 130
    //   503: iload 15
    //   505: iconst_3
    //   506: if_icmpne -49 -> 457
    //   509: aload 19
    //   511: astore 27
    //   513: aload 18
    //   515: astore 20
    //   517: iload 16
    //   519: istore 22
    //   521: aload 27
    //   523: astore 23
    //   525: aconst_null
    //   526: astore 21
    //   528: goto -398 -> 130
    // Local variable table:
    //   start	length	slot	name	signature
    //   0	531	0	this	de
    //   0	531	1	paramInputStream	java.io.InputStream
    //   1	443	2	localObject1	Object
    //   3	442	3	localObject2	Object
    //   5	441	4	bool1	boolean
    //   8	440	5	localObject3	Object
    //   11	439	6	str1	String
    //   14	438	7	str2	String
    //   166	3	8	localIOException	java.io.IOException
    //   28	149	9	arrayOfByte1	byte[]
    //   39	13	10	localByteArrayInputStream	java.io.ByteArrayInputStream
    //   181	7	11	localXmlPullParserException1	org.xmlpull.v1.XmlPullParserException
    //   47	165	12	localXmlPullParser	org.xmlpull.v1.XmlPullParser
    //   422	7	13	localObject4	Object
    //   407	7	14	localXmlPullParserException2	org.xmlpull.v1.XmlPullParserException
    //   67	440	15	i	int
    //   70	448	16	bool2	boolean
    //   73	416	17	localObject5	Object
    //   76	438	18	localObject6	Object
    //   79	431	19	localObject7	Object
    //   116	400	20	localObject8	Object
    //   120	407	21	localObject9	Object
    //   124	396	22	bool3	boolean
    //   128	396	23	localObject10	Object
    //   137	3	24	j	int
    //   145	15	25	localObject11	Object
    //   459	15	26	localObject12	Object
    //   511	11	27	localObject13	Object
    //   209	138	28	bool4	boolean
    //   218	165	29	str3	String
    //   482	15	30	localObject14	Object
    //   24	3	31	arrayOfByte2	byte[]
    // Exception table:
    //   from	to	target	type
    //   16	26	166	java/io/IOException
    //   41	60	181	org/xmlpull/v1/XmlPullParserException
    //   60	69	407	org/xmlpull/v1/XmlPullParserException
    //   93	114	407	org/xmlpull/v1/XmlPullParserException
    //   130	139	407	org/xmlpull/v1/XmlPullParserException
    //   202	240	407	org/xmlpull/v1/XmlPullParserException
    //   245	264	407	org/xmlpull/v1/XmlPullParserException
    //   267	277	407	org/xmlpull/v1/XmlPullParserException
    //   285	295	407	org/xmlpull/v1/XmlPullParserException
    //   303	313	407	org/xmlpull/v1/XmlPullParserException
    //   318	333	407	org/xmlpull/v1/XmlPullParserException
    //   336	346	407	org/xmlpull/v1/XmlPullParserException
    //   355	372	407	org/xmlpull/v1/XmlPullParserException
    //   372	389	407	org/xmlpull/v1/XmlPullParserException
    //   397	407	407	org/xmlpull/v1/XmlPullParserException
    //   60	69	422	finally
    //   93	114	422	finally
    //   130	139	422	finally
    //   202	240	422	finally
    //   245	264	422	finally
    //   267	277	422	finally
    //   285	295	422	finally
    //   303	313	422	finally
    //   318	333	422	finally
    //   336	346	422	finally
    //   355	372	422	finally
    //   372	389	422	finally
    //   397	407	422	finally
    //   409	422	422	finally
  }
}


/* Location:           C:\Users\pooya\Desktop\bc.jar
 * Qualified Name:     com.viber.voip.registration.de
 * JD-Core Version:    0.7.0.1
 */