package com.actionbarsherlock.widget;

final class ActivityChooserModel$HistoryLoader
  implements Runnable
{
  private ActivityChooserModel$HistoryLoader(ActivityChooserModel paramActivityChooserModel) {}
  
  /* Error */
  public void run()
  {
    // Byte code:
    //   0: aload_0
    //   1: getfield 12	com/actionbarsherlock/widget/ActivityChooserModel$HistoryLoader:this$0	Lcom/actionbarsherlock/widget/ActivityChooserModel;
    //   4: invokestatic 31	com/actionbarsherlock/widget/ActivityChooserModel:access$400	(Lcom/actionbarsherlock/widget/ActivityChooserModel;)Landroid/content/Context;
    //   7: aload_0
    //   8: getfield 12	com/actionbarsherlock/widget/ActivityChooserModel$HistoryLoader:this$0	Lcom/actionbarsherlock/widget/ActivityChooserModel;
    //   11: invokestatic 35	com/actionbarsherlock/widget/ActivityChooserModel:access$300	(Lcom/actionbarsherlock/widget/ActivityChooserModel;)Ljava/lang/String;
    //   14: invokevirtual 41	android/content/Context:openFileInput	(Ljava/lang/String;)Ljava/io/FileInputStream;
    //   17: astore_2
    //   18: invokestatic 47	android/util/Xml:newPullParser	()Lorg/xmlpull/v1/XmlPullParser;
    //   21: astore 11
    //   23: aload 11
    //   25: aload_2
    //   26: aconst_null
    //   27: invokeinterface 53 3 0
    //   32: iconst_0
    //   33: istore 12
    //   35: iload 12
    //   37: iconst_1
    //   38: if_icmpeq +21 -> 59
    //   41: iload 12
    //   43: iconst_2
    //   44: if_icmpeq +15 -> 59
    //   47: aload 11
    //   49: invokeinterface 57 1 0
    //   54: istore 12
    //   56: goto -21 -> 35
    //   59: ldc 59
    //   61: aload 11
    //   63: invokeinterface 63 1 0
    //   68: invokevirtual 69	java/lang/String:equals	(Ljava/lang/Object;)Z
    //   71: ifne +58 -> 129
    //   74: new 23	org/xmlpull/v1/XmlPullParserException
    //   77: dup
    //   78: ldc 71
    //   80: invokespecial 74	org/xmlpull/v1/XmlPullParserException:<init>	(Ljava/lang/String;)V
    //   83: athrow
    //   84: astore 8
    //   86: invokestatic 77	com/actionbarsherlock/widget/ActivityChooserModel:access$1100	()Ljava/lang/String;
    //   89: new 79	java/lang/StringBuilder
    //   92: dup
    //   93: invokespecial 80	java/lang/StringBuilder:<init>	()V
    //   96: ldc 82
    //   98: invokevirtual 86	java/lang/StringBuilder:append	(Ljava/lang/String;)Ljava/lang/StringBuilder;
    //   101: aload_0
    //   102: getfield 12	com/actionbarsherlock/widget/ActivityChooserModel$HistoryLoader:this$0	Lcom/actionbarsherlock/widget/ActivityChooserModel;
    //   105: invokestatic 35	com/actionbarsherlock/widget/ActivityChooserModel:access$300	(Lcom/actionbarsherlock/widget/ActivityChooserModel;)Ljava/lang/String;
    //   108: invokevirtual 86	java/lang/StringBuilder:append	(Ljava/lang/String;)Ljava/lang/StringBuilder;
    //   111: invokevirtual 89	java/lang/StringBuilder:toString	()Ljava/lang/String;
    //   114: aload 8
    //   116: invokestatic 95	android/util/Log:e	(Ljava/lang/String;Ljava/lang/String;Ljava/lang/Throwable;)I
    //   119: pop
    //   120: aload_2
    //   121: ifnull +7 -> 128
    //   124: aload_2
    //   125: invokevirtual 100	java/io/FileInputStream:close	()V
    //   128: return
    //   129: new 102	java/util/ArrayList
    //   132: dup
    //   133: invokespecial 103	java/util/ArrayList:<init>	()V
    //   136: astore 13
    //   138: aload 11
    //   140: invokeinterface 57 1 0
    //   145: istore 14
    //   147: iload 14
    //   149: iconst_1
    //   150: if_icmpne +77 -> 227
    //   153: aload_0
    //   154: getfield 12	com/actionbarsherlock/widget/ActivityChooserModel$HistoryLoader:this$0	Lcom/actionbarsherlock/widget/ActivityChooserModel;
    //   157: invokestatic 107	com/actionbarsherlock/widget/ActivityChooserModel:access$500	(Lcom/actionbarsherlock/widget/ActivityChooserModel;)Ljava/lang/Object;
    //   160: astore 15
    //   162: aload 15
    //   164: monitorenter
    //   165: new 109	java/util/LinkedHashSet
    //   168: dup
    //   169: aload 13
    //   171: invokespecial 112	java/util/LinkedHashSet:<init>	(Ljava/util/Collection;)V
    //   174: astore 16
    //   176: aload_0
    //   177: getfield 12	com/actionbarsherlock/widget/ActivityChooserModel$HistoryLoader:this$0	Lcom/actionbarsherlock/widget/ActivityChooserModel;
    //   180: invokestatic 116	com/actionbarsherlock/widget/ActivityChooserModel:access$600	(Lcom/actionbarsherlock/widget/ActivityChooserModel;)Ljava/util/List;
    //   183: astore 18
    //   185: iconst_m1
    //   186: aload 18
    //   188: invokeinterface 121 1 0
    //   193: iadd
    //   194: istore 19
    //   196: iload 19
    //   198: iflt +179 -> 377
    //   201: aload 16
    //   203: aload 18
    //   205: iload 19
    //   207: invokeinterface 125 2 0
    //   212: checkcast 127	com/actionbarsherlock/widget/ActivityChooserModel$HistoricalRecord
    //   215: invokeinterface 132 2 0
    //   220: pop
    //   221: iinc 19 255
    //   224: goto -28 -> 196
    //   227: iload 14
    //   229: iconst_3
    //   230: if_icmpeq -92 -> 138
    //   233: iload 14
    //   235: iconst_4
    //   236: if_icmpeq -98 -> 138
    //   239: ldc 134
    //   241: aload 11
    //   243: invokeinterface 63 1 0
    //   248: invokevirtual 69	java/lang/String:equals	(Ljava/lang/Object;)Z
    //   251: ifne +61 -> 312
    //   254: new 23	org/xmlpull/v1/XmlPullParserException
    //   257: dup
    //   258: ldc 136
    //   260: invokespecial 74	org/xmlpull/v1/XmlPullParserException:<init>	(Ljava/lang/String;)V
    //   263: athrow
    //   264: astore 5
    //   266: invokestatic 77	com/actionbarsherlock/widget/ActivityChooserModel:access$1100	()Ljava/lang/String;
    //   269: new 79	java/lang/StringBuilder
    //   272: dup
    //   273: invokespecial 80	java/lang/StringBuilder:<init>	()V
    //   276: ldc 82
    //   278: invokevirtual 86	java/lang/StringBuilder:append	(Ljava/lang/String;)Ljava/lang/StringBuilder;
    //   281: aload_0
    //   282: getfield 12	com/actionbarsherlock/widget/ActivityChooserModel$HistoryLoader:this$0	Lcom/actionbarsherlock/widget/ActivityChooserModel;
    //   285: invokestatic 35	com/actionbarsherlock/widget/ActivityChooserModel:access$300	(Lcom/actionbarsherlock/widget/ActivityChooserModel;)Ljava/lang/String;
    //   288: invokevirtual 86	java/lang/StringBuilder:append	(Ljava/lang/String;)Ljava/lang/StringBuilder;
    //   291: invokevirtual 89	java/lang/StringBuilder:toString	()Ljava/lang/String;
    //   294: aload 5
    //   296: invokestatic 95	android/util/Log:e	(Ljava/lang/String;Ljava/lang/String;Ljava/lang/Throwable;)I
    //   299: pop
    //   300: aload_2
    //   301: ifnull -173 -> 128
    //   304: aload_2
    //   305: invokevirtual 100	java/io/FileInputStream:close	()V
    //   308: return
    //   309: astore 7
    //   311: return
    //   312: aload 13
    //   314: new 127	com/actionbarsherlock/widget/ActivityChooserModel$HistoricalRecord
    //   317: dup
    //   318: aload 11
    //   320: aconst_null
    //   321: ldc 138
    //   323: invokeinterface 142 3 0
    //   328: aload 11
    //   330: aconst_null
    //   331: ldc 144
    //   333: invokeinterface 142 3 0
    //   338: invokestatic 150	java/lang/Long:parseLong	(Ljava/lang/String;)J
    //   341: aload 11
    //   343: aconst_null
    //   344: ldc 152
    //   346: invokeinterface 142 3 0
    //   351: invokestatic 158	java/lang/Float:parseFloat	(Ljava/lang/String;)F
    //   354: invokespecial 161	com/actionbarsherlock/widget/ActivityChooserModel$HistoricalRecord:<init>	(Ljava/lang/String;JF)V
    //   357: invokeinterface 162 2 0
    //   362: pop
    //   363: goto -225 -> 138
    //   366: astore_3
    //   367: aload_2
    //   368: ifnull +7 -> 375
    //   371: aload_2
    //   372: invokevirtual 100	java/io/FileInputStream:close	()V
    //   375: aload_3
    //   376: athrow
    //   377: aload 18
    //   379: invokeinterface 121 1 0
    //   384: aload 16
    //   386: invokeinterface 163 1 0
    //   391: if_icmpne +18 -> 409
    //   394: aload 15
    //   396: monitorexit
    //   397: aload_2
    //   398: ifnull -270 -> 128
    //   401: aload_2
    //   402: invokevirtual 100	java/io/FileInputStream:close	()V
    //   405: return
    //   406: astore 25
    //   408: return
    //   409: aload 18
    //   411: invokeinterface 166 1 0
    //   416: aload 18
    //   418: aload 16
    //   420: invokeinterface 170 2 0
    //   425: pop
    //   426: aload_0
    //   427: getfield 12	com/actionbarsherlock/widget/ActivityChooserModel$HistoryLoader:this$0	Lcom/actionbarsherlock/widget/ActivityChooserModel;
    //   430: iconst_1
    //   431: invokestatic 174	com/actionbarsherlock/widget/ActivityChooserModel:access$702	(Lcom/actionbarsherlock/widget/ActivityChooserModel;Z)Z
    //   434: pop
    //   435: aload_0
    //   436: getfield 12	com/actionbarsherlock/widget/ActivityChooserModel$HistoryLoader:this$0	Lcom/actionbarsherlock/widget/ActivityChooserModel;
    //   439: invokestatic 178	com/actionbarsherlock/widget/ActivityChooserModel:access$1000	(Lcom/actionbarsherlock/widget/ActivityChooserModel;)Landroid/os/Handler;
    //   442: new 180	com/actionbarsherlock/widget/ActivityChooserModel$HistoryLoader$1
    //   445: dup
    //   446: aload_0
    //   447: invokespecial 183	com/actionbarsherlock/widget/ActivityChooserModel$HistoryLoader$1:<init>	(Lcom/actionbarsherlock/widget/ActivityChooserModel$HistoryLoader;)V
    //   450: invokevirtual 189	android/os/Handler:post	(Ljava/lang/Runnable;)Z
    //   453: pop
    //   454: aload 15
    //   456: monitorexit
    //   457: aload_2
    //   458: ifnull -330 -> 128
    //   461: aload_2
    //   462: invokevirtual 100	java/io/FileInputStream:close	()V
    //   465: return
    //   466: astore 24
    //   468: return
    //   469: astore 17
    //   471: aload 15
    //   473: monitorexit
    //   474: aload 17
    //   476: athrow
    //   477: astore 10
    //   479: return
    //   480: astore 4
    //   482: goto -107 -> 375
    //   485: astore_1
    //   486: return
    // Local variable table:
    //   start	length	slot	name	signature
    //   0	487	0	this	HistoryLoader
    //   485	1	1	localFileNotFoundException	java.io.FileNotFoundException
    //   17	445	2	localFileInputStream	java.io.FileInputStream
    //   366	10	3	localObject1	Object
    //   480	1	4	localIOException1	java.io.IOException
    //   264	31	5	localIOException2	java.io.IOException
    //   309	1	7	localIOException3	java.io.IOException
    //   84	31	8	localXmlPullParserException	org.xmlpull.v1.XmlPullParserException
    //   477	1	10	localIOException4	java.io.IOException
    //   21	321	11	localXmlPullParser	org.xmlpull.v1.XmlPullParser
    //   33	22	12	i	int
    //   136	177	13	localArrayList	java.util.ArrayList
    //   145	92	14	j	int
    //   174	245	16	localLinkedHashSet	java.util.LinkedHashSet
    //   469	6	17	localObject3	Object
    //   183	234	18	localList	java.util.List
    //   194	28	19	k	int
    //   466	1	24	localIOException5	java.io.IOException
    //   406	1	25	localIOException6	java.io.IOException
    // Exception table:
    //   from	to	target	type
    //   18	32	84	org/xmlpull/v1/XmlPullParserException
    //   47	56	84	org/xmlpull/v1/XmlPullParserException
    //   59	84	84	org/xmlpull/v1/XmlPullParserException
    //   129	138	84	org/xmlpull/v1/XmlPullParserException
    //   138	147	84	org/xmlpull/v1/XmlPullParserException
    //   153	165	84	org/xmlpull/v1/XmlPullParserException
    //   239	264	84	org/xmlpull/v1/XmlPullParserException
    //   312	363	84	org/xmlpull/v1/XmlPullParserException
    //   474	477	84	org/xmlpull/v1/XmlPullParserException
    //   18	32	264	java/io/IOException
    //   47	56	264	java/io/IOException
    //   59	84	264	java/io/IOException
    //   129	138	264	java/io/IOException
    //   138	147	264	java/io/IOException
    //   153	165	264	java/io/IOException
    //   239	264	264	java/io/IOException
    //   312	363	264	java/io/IOException
    //   474	477	264	java/io/IOException
    //   304	308	309	java/io/IOException
    //   18	32	366	finally
    //   47	56	366	finally
    //   59	84	366	finally
    //   86	120	366	finally
    //   129	138	366	finally
    //   138	147	366	finally
    //   153	165	366	finally
    //   239	264	366	finally
    //   266	300	366	finally
    //   312	363	366	finally
    //   474	477	366	finally
    //   401	405	406	java/io/IOException
    //   461	465	466	java/io/IOException
    //   165	196	469	finally
    //   201	221	469	finally
    //   377	397	469	finally
    //   409	457	469	finally
    //   471	474	469	finally
    //   124	128	477	java/io/IOException
    //   371	375	480	java/io/IOException
    //   0	18	485	java/io/FileNotFoundException
  }
}


/* Location:           C:\Users\pooya\Desktop\bc.jar
 * Qualified Name:     com.actionbarsherlock.widget.ActivityChooserModel.HistoryLoader
 * JD-Core Version:    0.7.0.1
 */